{
    "textures": {
    	"earth": {
    		"file":		"textures/wallvertical.png",
    		"wrap":		true,
    	},
		"wallvertical": {
//			"file":		"textures/BG_Wall_Vertical.png",
			"file":		"textures/cropped_vwall.png",
			"wrap":		false,
		},
		"wallhorizontal": {
//			"file":		"textures/BG_Wall_Mid.png",
			"file":		"textures/cropped_hwall.png",
			"wrap":		false,
		},
		"floor": {
			"file": 	"textures/BG_Tile.png",
			"wrap": 	true,
		},
    	"dude": {      
    		"file": 	"textures/walking.png",
    		"wrap":  	false,
    		"strip":	{
    			"size":		4,
    			"rows":		1,
    			"cols":		4,
    			"first":	0
    		}
    	},
		"laserAnimation": {
			"file": 	"textures/laseranimation.png",
			"wrap":  	false,
			"strip":	{
				"size":		6,
				"rows":		1,
				"cols":		6,
				"first":	0
			}
		},
        "goal": { 
         	"file":		"textures/exit.png",
         	"wrap":		false,
         },
		"defaultDude": {
			"file": 	"textures/Player.png",
			"wrap": 	false,
		},
		"guard": {
			"file": 	"textures/guardsprite.png",
			"wrap": 	false,
		},
		"box1": {
			"file": 	"textures/BG_Box3.png",
			"wrap": 	false,
		},
		"box2": {
			"file": 	"textures/BG_Box2.png",
			"wrap": 	false,
		},
		"box3": {
			"file": 	"textures/BG_Box4.png",
			"wrap": 	false,
		},
        "door": {
          "file": 	    "textures/doorC.png",
          "wrap":     	false,
        },
        "switch": {
          "file": 	    "textures/switchOff.png",
          "wrap":     	false,
        },
		"laser": {
			"file": 	"textures/laser.png",
			"wrap": 	true,
		},
		"boxDude": {
			"file": 	"textures/boxdude.png",
			"wrap": 	false,
		},
		"key": 		{
			"file": 	"textures/key.png",
			"wrap": 	false,
		},
		"pause":	{
			"file":		"textures/temp_pause.png",
			"wrap": 	false,
		},
  	},
  	"fonts": {
  		"display": {
  			"file": 	"fonts/MarkerFelt.ttf",
  			"size": 	64
  		},
  	},
}